pyUnderLX/__init__.py
pyUnderLX/api.py
pyUnderLX/consts.py
pyUnderLX/occurrences.py
pyUnderLX-1.0.1.dist-info/LICENSE
pyUnderLX-1.0.1.dist-info/METADATA
pyUnderLX-1.0.1.dist-info/WHEEL
pyUnderLX-1.0.1.dist-info/top_level.txt
pyUnderLX-1.0.1.dist-info/zip-safe
pyUnderLX-1.0.1.dist-info/RECORD
